aiobananas/__init__.py
aiobananas/generics.py
aiobananas/package.py
aiobananas-4.0.1.post2.dist-info/METADATA
aiobananas-4.0.1.post2.dist-info/WHEEL
aiobananas-4.0.1.post2.dist-info/RECORD
