Metadata-Version: 2.1
Name: aiobananas
Version: 4.0.1.post2
Summary: aiobananas is an async version of banana-dev
License: MIT
Keywords: async,aiobananas,banana-dev,SDK,Banana client
Author: Bennett Hoffman
Author-email: benn.hoffman@gmail.com
Requires-Python: >=3.10,<4.0
Classifier: License :: OSI Approved :: MIT License
Classifier: Programming Language :: Python :: 3
Classifier: Programming Language :: Python :: 3.10
Classifier: Programming Language :: Python :: 3.11
Requires-Dist: aiohttp (>=3.8.3,<4.0.0)
Requires-Dist: charset-normalizer (>=2.0.7,<3.0.0)
Requires-Dist: pydantic (>=1.10.2,<2.0.0)
